hpy12c.py
hpy12c-0.3.0.dist-info/LICENSE
hpy12c-0.3.0.dist-info/METADATA
hpy12c-0.3.0.dist-info/WHEEL
hpy12c-0.3.0.dist-info/top_level.txt
hpy12c-0.3.0.dist-info/RECORD
