Metadata-Version: 2.1
Name: hpy12c
Version: 0.3.0
Summary: HPy12C - A pure python implementation of HP-12C financial calculator
Home-page: https://github.com/risparfinance/hpy12c
Author: Rispar
Author-email: tecnologia@rispar.com.br
License: Apache License 2.0
Platform: UNKNOWN
Classifier: Development Status :: 3 - Alpha
Classifier: License :: OSI Approved :: Apache Software License
Classifier: Operating System :: OS Independent
Classifier: Programming Language :: Python :: 3
Classifier: Programming Language :: Python :: 3.8
Classifier: Topic :: Utilities
License-File: LICENSE
